evo/__init__.py
evo/evo_framework/__init__.py
evo/evo_framework/control/CObject.py
evo/evo_framework/control/__init__.py
evo/evo_framework/core/__init__.py
evo/evo_framework/core/evo_core_api/__init__.py
evo/evo_framework/core/evo_core_api/automation/entity.yaml
evo/evo_framework/core/evo_core_api/control/CApi.py
evo/evo_framework/core/evo_core_api/control/CApiFlow.py
evo/evo_framework/core/evo_core_api/control/__init__.py
evo/evo_framework/core/evo_core_api/entity/EAction.py
evo/evo_framework/core/evo_core_api/entity/EActionItem.py
evo/evo_framework/core/evo_core_api/entity/EActionTask.py
evo/evo_framework/core/evo_core_api/entity/EApi.py
evo/evo_framework/core/evo_core_api/entity/EApiAudio.py
evo/evo_framework/core/evo_core_api/entity/EApiConfig.py
evo/evo_framework/core/evo_core_api/entity/EApiEntity.py
evo/evo_framework/core/evo_core_api/entity/EApiFile.py
evo/evo_framework/core/evo_core_api/entity/EApiImage.py
evo/evo_framework/core/evo_core_api/entity/EApiItem.py
evo/evo_framework/core/evo_core_api/entity/EApiVideo.py
evo/evo_framework/core/evo_core_api/entity/ERequest.py
evo/evo_framework/core/evo_core_api/entity/EResponse.py
evo/evo_framework/core/evo_core_api/entity/EnumApiAction.py
evo/evo_framework/core/evo_core_api/entity/EnumApiCompress.py
evo/evo_framework/core/evo_core_api/entity/EnumApiCrypto.py
evo/evo_framework/core/evo_core_api/entity/EnumApiType.py
evo/evo_framework/core/evo_core_api/entity/EnumLanguage.py
evo/evo_framework/core/evo_core_api/entity/__init__.py
evo/evo_framework/core/evo_core_api/entity/cs/EApiAudio.cs
evo/evo_framework/core/evo_core_api/entity/cs/EApiFile.cs
evo/evo_framework/core/evo_core_api/entity/cs/EApiImage.cs
evo/evo_framework/core/evo_core_api/entity/cs/EApiVideo.cs
evo/evo_framework/core/evo_core_api/entity/evo_core_api_entity_pb2.py
evo/evo_framework/core/evo_core_api/proto/build_proto.sh
evo/evo_framework/core/evo_core_api/proto/entity/cs/EvoCoreApiEntity.cs
evo_framework-22024.5.12.dist-info/METADATA
evo_framework-22024.5.12.dist-info/WHEEL
evo_framework-22024.5.12.dist-info/RECORD
